{
    "info": {
        "title": "Sách Kỳ Quan Thế Giới ( World's Greatest Wonders ) - Hình ảnh Minh Họa 3D Giới Thiệu Chi Tiết Về 30 Kỳ Quan Thiên Nhiên Và Nhân Tạo Tuyệt Đẹp - Á Châu Books, Bìa Cứng, In Màu",
        "author": "Joyce Meyer"
    },
    "rating": {
        "total_rating": 4.6,
        "number_of_rating": 17
    },
    "details": {
        "Công ty phát hành": "Công ty CP Đầu tư và Phát triển giáo dục quốc tế Á Châu",
        "Ngày xuất bản": "2021-03-25 09:21:18",
        "Loại bìa": "Bìa cứng",
        "Số trang": "256",
        "Nhà xuất bản": "Nhà Xuất Bản Lao Động Hà Nội"
    },
    "reviews": [
        {
            "reviewer": {
                "name": "CucPhuong Tang",
                "date": "Đã tham gia 6 năm",
                "review_count": "76 Đánh giá",
                "liked_count": "9 Lượt cảm ơn"
            },
            "review": {
                "rating": 5,
                "title": "Cực kì hài lòng",
                "content": "sách đẹp. giao hàng nhanh. đóng gói kỹ lưỡng."
            }
        },
        {
            "reviewer": {
                "name": "Chu Huy Long",
                "date": "Đã tham gia 9 năm",
                "review_count": "19 Đánh giá",
                "liked_count": "4 Lượt cảm ơn"
            },
            "review": {
                "rating": 5,
                "title": "Cực kì hài lòng",
                "content": "Sách đẹp, bọc cẩn thận. Giao nhanh."
            }
        },
        {
            "reviewer": {
                "name": "Đức Nguyễn Hòa",
                "date": "Đã tham gia 2 năm",
                "review_count": "17 Đánh giá",
                "liked_count": "0 Lượt cảm ơn"
            },
            "review": {
                "rating": 5,
                "title": "Cực kì hài lòng",
                "content": ""
            }
        },
        {
            "reviewer": {
                "name": "Truong Binh",
                "date": "Đã tham gia 12 năm",
                "review_count": "15 Đánh giá",
                "liked_count": "0 Lượt cảm ơn"
            },
            "review": {
                "rating": 5,
                "title": "Cực kì hài lòng",
                "content": "Full of quality pics and info. However, content is a little bit short."
            }
        },
        {
            "reviewer": {
                "name": "KIm Ngân Bùi",
                "date": "Đã tham gia 10 năm",
                "review_count": "18 Đánh giá",
                "liked_count": "1 Lượt cảm ơn"
            },
            "review": {
                "rating": 5,
                "title": "Cực kì hài lòng",
                "content": "sách rất hay. muốn mua trọn bộ quá. mong giảm giá nhiều"
            }
        }
    ]
}